nucsoi/__init__.py
nucsoi/nucsoi.py
nucsoi/scripts/fastp.py
nucsoi/scripts/map_to_plasmid.py
nucsoi-1.0.0.dist-info/licenses/LICENSE
nucsoi-1.0.0.dist-info/METADATA
nucsoi-1.0.0.dist-info/WHEEL
nucsoi-1.0.0.dist-info/entry_points.txt
nucsoi-1.0.0.dist-info/top_level.txt
nucsoi-1.0.0.dist-info/RECORD
