Metadata-Version: 2.4
Name: nucsoi
Version: 1.0.0
Summary: Nuclease Cleavage Site and Overhang Identification
Home-page: https://github.com/Matt115A/NuCSOI
Author: Matthew Penner
Author-email: Matthew Penner <mp957@cam.ac.uk>
Maintainer-email: Matthew Penner <mp957@cam.ac.uk>
License: MIT
Project-URL: Homepage, https://github.com/Matt115A/NuCSOI
Project-URL: Documentation, https://github.com/Matt115A/NuCSOI#readme
Project-URL: Repository, https://github.com/Matt115A/NuCSOI
Project-URL: Bug Tracker, https://github.com/Matt115A/NuCSOI/issues
Keywords: bioinformatics,nuclease,cleavage,sequencing,coverage,analysis
Classifier: Development Status :: 4 - Beta
Classifier: Intended Audience :: Science/Research
Classifier: Topic :: Scientific/Engineering :: Bio-Informatics
Classifier: License :: OSI Approved :: MIT License
Classifier: Programming Language :: Python :: 3
Classifier: Programming Language :: Python :: 3.10
Classifier: Operating System :: OS Independent
Requires-Python: >=3.10,<3.11
License-File: LICENSE
Requires-Dist: pandas~=2.3.3
Requires-Dist: numpy~=2.2.1
Requires-Dist: scipy~=1.15.3
Requires-Dist: pyyaml~=6.0.3
Requires-Dist: tqdm~=4.67.1
Requires-Dist: biopython~=1.85.0
Requires-Dist: pysam~=0.23.3
Requires-Dist: matplotlib~=3.10.7
Requires-Dist: seaborn~=0.13.2
Requires-Dist: logomaker~=0.8.7
Provides-Extra: dev
Requires-Dist: pytest>=6.0; extra == "dev"
Requires-Dist: pytest-cov>=2.0; extra == "dev"
Requires-Dist: black>=21.0; extra == "dev"
Requires-Dist: flake8>=3.8; extra == "dev"
Requires-Dist: mypy>=0.800; extra == "dev"
Dynamic: author
Dynamic: home-page
Dynamic: license-file
Dynamic: requires-python
